dszoro/__init__.py
dszoro/program.py
dszoro-0.0.9.dist-info/LICENSE
dszoro-0.0.9.dist-info/METADATA
dszoro-0.0.9.dist-info/WHEEL
dszoro-0.0.9.dist-info/top_level.txt
dszoro-0.0.9.dist-info/RECORD
